toon_parse_mcp/server.py
toon_parse_mcp/utils.py
toon_parse_mcp-1.0.4b0.dist-info/licenses/LICENSE
toon_parse_mcp-1.0.4b0.dist-info/METADATA
toon_parse_mcp-1.0.4b0.dist-info/WHEEL
toon_parse_mcp-1.0.4b0.dist-info/top_level.txt
toon_parse_mcp-1.0.4b0.dist-info/RECORD
