Metadata-Version: 2.4
Name: toon-parse-mcp
Version: 1.0.4b0
Summary: Token optimization MCP server that reduces LLM context by stripping code comments and converting data formats to TOON
Author-email: Ankit Pal <ankitpal181@gmail.com>
Project-URL: Download, https://pypi.org/project/toon-parse-mcp/#files
Project-URL: Source, https://github.com/ankitpal181/toon-parse-mcp
Project-URL: Bug Tracker, https://github.com/ankitpal181/toon-parse-mcp/issues
Project-URL: Funding, https://github.com/sponsors/ankitpal181
Keywords: mcp,model-context-protocol,toon,optimization,llm
Classifier: Programming Language :: Python :: 3.10
Classifier: Programming Language :: Python :: 3.11
Classifier: Programming Language :: Python :: 3.12
Classifier: Programming Language :: Python :: 3.13
Classifier: Topic :: Software Development
Classifier: License :: OSI Approved :: MIT License
Classifier: Operating System :: OS Independent
Classifier: Intended Audience :: Developers
Classifier: Intended Audience :: Education
Classifier: Development Status :: 4 - Beta
Requires-Python: >=3.10
License-File: LICENSE
Requires-Dist: mcp>=1.25.0
Requires-Dist: toon-parse>=2.4.3
Dynamic: license-file
